{
    "monday": {
        "breakfast": [
            "collagenDrink",
            "breakfastSandwich"
        ],
        "lunch": [
            "eatOutLunch"
        ],
        "dinner": [
            "TJsFrozenDinners"
        ]
    },
    "tuesday": {
        "breakfast": [
            "collagenDrink",
            "breakfastSandwich"
        ],
        "lunch": [
            "eatOutLunch"
        ],
        "dinner": [
            "eatOutDinner"
        ]
    },
    "wednesday": {
        "breakfast": [
            "collagenDrink",
            "proteinShake",
            "eatOutBreakfast200"
        ],
        "lunch": [
            "eatOutLunch"
        ],
        "dinner": [
            "eatOutDinner"
        ]
    },
    "thursday": {
        "breakfast": [
            "breakfastSandwich"
        ],
        "lunch": [],
        "dinner": []
    },
    "friday": {
        "breakfast": [],
        "lunch": [],
        "dinner": []
    },
    "saturday": {
        "breakfast": [],
        "lunch": [],
        "dinner": []
    },
    "sunday": {
        "breakfast": [],
        "lunch": [],
        "dinner": []
    }
}